[{"name":"Agahra","code":"233794","panchayatCode":"100709","panchayatName":"Agahara"},{"name":"Asawn","code":"233822","panchayatCode":"100710","panchayatName":"Awari"},{"name":"Askaranpur","code":"233796","panchayatCode":"100717","panchayatName":"Hathisar"},{"name":"Askaranpur","code":"233783","panchayatCode":"100709","panchayatName":"Agahara"},{"name":"Asoia","code":"233831","panchayatCode":"100720","panchayatName":"Mirzapur"},{"name":"Asoiya","code":"957884","panchayatCode":"","panchayatName":""},{"name":"Ata","code":"233826","panchayatCode":"100728","panchayatName":"Shilhauri"},{"name":"Awari","code":"233824","panchayatCode":"100710","panchayatName":"Awari"},{"name":"Awdal Patti","code":"233777","panchayatCode":"100726","panchayatName":"Rasulpur"},{"name":"Bahuara Patti","code":"233799","panchayatCode":"100711","panchayatName":"Bahuwara Patti"},{"name":"Baidapur","code":"233850","panchayatCode":"100724","panchayatName":"Olhanpur"},{"name":"Bardahia","code":"233830","panchayatCode":"100712","panchayatName":"Bardahia"},{"name":"Bazid Bhoraha","code":"233812","panchayatCode":"100720","panchayatName":"Mirzapur"},{"name":"Bazidpur","code":"233820","panchayatCode":"100727","panchayatName":"Salimapur"},{"name":"Bhalui","code":"233847","panchayatCode":"100712","panchayatName":"Bardahia"},{"name":"Bhawalpur","code":"233868","panchayatCode":"100713","panchayatName":"Bhawalpur"},{"name":"Bheria","code":"233869","panchayatCode":"100713","panchayatName":"Bhawalpur"},{"name":"Bhuwalpur","code":"233842","panchayatCode":"100714","panchayatName":"Bhualpur"},{"name":"Bikrampur","code":"233865","panchayatCode":"100723","panchayatName":"Nautan"},{"name":"Bikrampur","code":"233853","panchayatCode":"100723","panchayatName":"Nautan"},{"name":"Bin Bahuara","code":"233780","panchayatCode":"100711","panchayatName":"Bahuwara Patti"},{"name":"Bishunpur Jagdish","code":"233870","panchayatCode":"100713","panchayatName":"Bhawalpur"},{"name":"Bishunpura","code":"233792","panchayatCode":"100715","panchayatName":"Gaura"},{"name":"Chainpur","code":"233862","panchayatCode":"100716","panchayatName":"Hasanpura"},{"name":"Chanda","code":"233849","panchayatCode":"100709","panchayatName":"Agahara"},{"name":"Chanda","code":"233815","panchayatCode":"100709","panchayatName":"Agahara"},{"name":"Channa","code":"233833","panchayatCode":"100718","panchayatName":"Israuli"},{"name":"Channa","code":"233806","panchayatCode":"100718","panchayatName":"Israuli"},{"name":"Damodarpur","code":"233772","panchayatCode":"100725","panchayatName":"Rampur"},{"name":"Damodarpur","code":"233828","panchayatCode":"100712","panchayatName":"Bardahia"},{"name":"Dealpur","code":"233804","panchayatCode":"100719","panchayatName":"Madhopur"},{"name":"Dew Bahuara","code":"233801","panchayatCode":"100711","panchayatName":"Bahuwara Patti"},{"name":"Dharampur","code":"233852","panchayatCode":"100723","panchayatName":"Nautan"},{"name":"Dharmauli","code":"233841","panchayatCode":"100714","panchayatName":"Bhualpur"},{"name":"Dhenuki","code":"958239","panchayatCode":"","panchayatName":""},{"name":"Gaura","code":"233791","panchayatCode":"100715","panchayatName":"Gaura"},{"name":"Ghurna","code":"233860","panchayatCode":"100716","panchayatName":"Hasanpura"},{"name":"Gopalpur","code":"233782","panchayatCode":"100709","panchayatName":"Agahara"},{"name":"Gopalpur","code":"233795","panchayatCode":"100717","panchayatName":"Hathisar"},{"name":"Hakam","code":"233835","panchayatCode":"100719","panchayatName":"Madhopur"},{"name":"Harpur","code":"233770","panchayatCode":"100725","panchayatName":"Rampur"},{"name":"Hasanpura","code":"233857","panchayatCode":"100716","panchayatName":"Hasanpura"},{"name":"Hathsar","code":"233789","panchayatCode":"100717","panchayatName":"Hathisar"},{"name":"Hirmi","code":"233807","panchayatCode":"100718","panchayatName":"Israuli"},{"name":"Israuli","code":"233810","panchayatCode":"100718","panchayatName":"Israuli"},{"name":"Jagdishpur","code":"233803","panchayatCode":"100719","panchayatName":"Madhopur"},{"name":"Jalalpur","code":"233838","panchayatCode":"100721","panchayatName":"Mubarakpur"},{"name":"Jamalpur","code":"233871","panchayatCode":"100713","panchayatName":"Bhawalpur"},{"name":"Jawania","code":"233797","panchayatCode":"100709","panchayatName":"Agahara"},{"name":"Jhakhra Birit","code":"233854","panchayatCode":"100716","panchayatName":"Hasanpura"},{"name":"Jodhauli","code":"233872","panchayatCode":"100713","panchayatName":"Bhawalpur"},{"name":"Karanpura","code":"233866","panchayatCode":"100723","panchayatName":"Nautan"},{"name":"Khalispur","code":"233790","panchayatCode":"100715","panchayatName":"Gaura"},{"name":"Kharauni","code":"233859","panchayatCode":"100716","panchayatName":"Hasanpura"},{"name":"Khurampur","code":"233773","panchayatCode":"100726","panchayatName":"Rasulpur"},{"name":"Kolhua","code":"233867","panchayatCode":"100713","panchayatName":"Bhawalpur"},{"name":"Kondhi","code":"233785","panchayatCode":"100717","panchayatName":"Hathisar"},{"name":"Lalapur","code":"233855","panchayatCode":"100716","panchayatName":"Hasanpura"},{"name":"Lerua","code":"233817","panchayatCode":"100729","panchayatName":"Tejpurwa"},{"name":"Madhopur","code":"233805","panchayatCode":"100719","panchayatName":"Madhopur"},{"name":"Mahammadpur","code":"233784","panchayatCode":"100717","panchayatName":"Hathisar"},{"name":"Majhaulia","code":"233776","panchayatCode":"100726","panchayatName":"Rasulpur"},{"name":"Marhaura Chattis","code":"233856","panchayatCode":"100716","panchayatName":"Hasanpura"},{"name":"Marhaura Khas","code":"958242","panchayatCode":"","panchayatName":""},{"name":"Marhaura Khurd","code":"958243","panchayatCode":"","panchayatName":""},{"name":"Marhaura Uttar","code":"958241","panchayatCode":"","panchayatName":""},{"name":"Masaha","code":"233798","panchayatCode":"100709","panchayatName":"Agahara"},{"name":"Mirzapur","code":"233813","panchayatCode":"100729","panchayatName":"Tejpurwa"},{"name":"Mobarakpur","code":"233863","panchayatCode":"100716","panchayatName":"Hasanpura"},{"name":"Mobarakpur","code":"233837","panchayatCode":"100721","panchayatName":"Mubarakpur"},{"name":"Mothaha","code":"233768","panchayatCode":"100722","panchayatName":"Narhar Pur"},{"name":"Narharpur","code":"233769","panchayatCode":"100722","panchayatName":"Narhar Pur"},{"name":"Narharpur Chamari","code":"233787","panchayatCode":"100717","panchayatName":"Hathisar"},{"name":"Nathua","code":"233819","panchayatCode":"100727","panchayatName":"Salimapur"},{"name":"Nautan","code":"233873","panchayatCode":"100723","panchayatName":"Nautan"},{"name":"Olhanpur","code":"233836","panchayatCode":"100724","panchayatName":"Olhanpur"},{"name":"Pakaha","code":"958240","panchayatCode":"","panchayatName":""},{"name":"Parari","code":"233786","panchayatCode":"100717","panchayatName":"Hathisar"},{"name":"Paterhi Baij","code":"233808","panchayatCode":"100718","panchayatName":"Israuli"},{"name":"Paterhi Jalal","code":"233809","panchayatCode":"100718","panchayatName":"Israuli"},{"name":"Piarpurwa","code":"233811","panchayatCode":"100718","panchayatName":"Israuli"},{"name":"Pojhi Buzurg","code":"233844","panchayatCode":"100714","panchayatName":"Bhualpur"},{"name":"Pojhikapur","code":"233845","panchayatCode":"100714","panchayatName":"Bhualpur"},{"name":"Pojhikpur","code":"233843","panchayatCode":"100714","panchayatName":"Bhualpur"},{"name":"Purbari Bhalui","code":"233846","panchayatCode":"100714","panchayatName":"Bhualpur"},{"name":"Rahimpur","code":"957593","panchayatCode":"","panchayatName":""},{"name":"Rahimpur Chhapia","code":"233861","panchayatCode":"100716","panchayatName":"Hasanpura"},{"name":"Raj Ganwan","code":"233802","panchayatCode":"100711","panchayatName":"Bahuwara Patti"},{"name":"Ram Chak","code":"233851","panchayatCode":"100712","panchayatName":"Bardahia"},{"name":"Rampur","code":"233771","panchayatCode":"100725","panchayatName":"Rampur"},{"name":"Rasulpur","code":"233781","panchayatCode":"100726","panchayatName":"Rasulpur"},{"name":"Rasulpur","code":"233775","panchayatCode":"100726","panchayatName":"Rasulpur"},{"name":"Repura","code":"233779","panchayatCode":"100711","panchayatName":"Bahuwara Patti"},{"name":"Rup Rahimpur","code":"233864","panchayatCode":"100716","panchayatName":"Hasanpura"},{"name":"Saikharauni","code":"233858","panchayatCode":"100716","panchayatName":"Hasanpura"},{"name":"Salimapur","code":"233821","panchayatCode":"100727","panchayatName":"Salimapur"},{"name":"Sardharae-Ke-Tola","code":"233788","panchayatCode":"100717","panchayatName":"Hathisar"},{"name":"Semar Sarae","code":"233800","panchayatCode":"100711","panchayatName":"Bahuwara Patti"},{"name":"Semarahia","code":"233823","panchayatCode":"100710","panchayatName":"Awari"},{"name":"Senduari","code":"233834","panchayatCode":"100719","panchayatName":"Madhopur"},{"name":"Shaani Chanda","code":"958244","panchayatCode":"","panchayatName":""},{"name":"Shahbazpur","code":"233839","panchayatCode":"100721","panchayatName":"Mubarakpur"},{"name":"Sherpur","code":"233793","panchayatCode":"100709","panchayatName":"Agahara"},{"name":"Sihoria","code":"233829","panchayatCode":"100712","panchayatName":"Bardahia"},{"name":"Silhauri","code":"233825","panchayatCode":"100728","panchayatName":"Shilhauri"},{"name":"Sisawa","code":"233774","panchayatCode":"100726","panchayatName":"Rasulpur"},{"name":"Siswa","code":"233778","panchayatCode":"100726","panchayatName":"Rasulpur"},{"name":"Suksena","code":"233840","panchayatCode":"100721","panchayatName":"Mubarakpur"},{"name":"Takina","code":"957575","panchayatCode":"","panchayatName":""},{"name":"Talpuraina","code":"233814","panchayatCode":"100720","panchayatName":"Mirzapur"},{"name":"Tehti","code":"233827","panchayatCode":"100728","panchayatName":"Shilhauri"},{"name":"Tejpurwa","code":"233816","panchayatCode":"100729","panchayatName":"Tejpurwa"},{"name":"Tenua","code":"233818","panchayatCode":"100727","panchayatName":"Salimapur"},{"name":"Tola Bhalui","code":"233848","panchayatCode":"100714","panchayatName":"Bhualpur"},{"name":"Ujari Seuduari","code":"233832","panchayatCode":"100718","panchayatName":"Israuli"},{"name":"Yaado Rahimpur","code":"957864","panchayatCode":"","panchayatName":""}]