[{"name":"Adilapur","code":"250673","panchayatCode":"99847","panchayatName":"Laheri"},{"name":"Agarsidehra","code":"250753","panchayatCode":"99837","panchayatName":"Agarsi Dihra"},{"name":"Amarsidehra","code":"250739","panchayatCode":"99842","panchayatName":"Kanjar"},{"name":"Amhaita","code":"250713","panchayatCode":"99837","panchayatName":"Agarsi Dihra"},{"name":"Andaur","code":"250763","panchayatCode":"99847","panchayatName":"Laheri"},{"name":"Andaur","code":"250675","panchayatCode":"99839","panchayatName":"Chitawn"},{"name":"Anhari","code":"250630","panchayatCode":"99841","panchayatName":"Gara"},{"name":"Athrolia","code":"250697","panchayatCode":"99843","panchayatName":"Kapasiya"},{"name":"Babuka Bahuara","code":"250620","panchayatCode":"99846","panchayatName":"Kuchhila"},{"name":"Baghel Dihra","code":"250792","panchayatCode":"99849","panchayatName":"Nauwan"},{"name":"Bahoranpur","code":"250730","panchayatCode":"99838","panchayatName":"Balathari"},{"name":"Bahuara","code":"250683","panchayatCode":"99844","panchayatName":"Kathrai"},{"name":"Bajaraha","code":"250721","panchayatCode":"99847","panchayatName":"Laheri"},{"name":"Balthari","code":"250717","panchayatCode":"99838","panchayatName":"Balathari"},{"name":"Baradih","code":"250672","panchayatCode":"99843","panchayatName":"Kapasiya"},{"name":"Baradih","code":"250707","panchayatCode":"99847","panchayatName":"Laheri"},{"name":"Barahuti Kalan","code":"250682","panchayatCode":"99840","panchayatName":"Chittaini"},{"name":"Barahuti Khurd","code":"250689","panchayatCode":"99840","panchayatName":"Chittaini"},{"name":"Bararhi","code":"250742","panchayatCode":"99842","panchayatName":"Kanjar"},{"name":"Bardiha","code":"250678","panchayatCode":"99840","panchayatName":"Chittaini"},{"name":"Barman Chak","code":"250664","panchayatCode":"99840","panchayatName":"Chittaini"},{"name":"Basu Dehra","code":"250798","panchayatCode":"99839","panchayatName":"Chitawn"},{"name":"Bathori","code":"250808","panchayatCode":"99839","panchayatName":"Chitawn"},{"name":"Bedwalia","code":"250700","panchayatCode":"99843","panchayatName":"Kapasiya"},{"name":"Benipur","code":"250628","panchayatCode":"99841","panchayatName":"Gara"},{"name":"Berukahi","code":"250660","panchayatCode":"99840","panchayatName":"Chittaini"},{"name":"Bhagatganj","code":"250777","panchayatCode":"99848","panchayatName":"Narwar"},{"name":"Bhagiratha","code":"250779","panchayatCode":"99848","panchayatName":"Narwar"},{"name":"Bhairopur","code":"250698","panchayatCode":"99843","panchayatName":"Kapasiya"},{"name":"Bhandera","code":"250681","panchayatCode":"99840","panchayatName":"Chittaini"},{"name":"Bharadih","code":"250688","panchayatCode":"99844","panchayatName":"Kathrai"},{"name":"Bharhua","code":"250776","panchayatCode":"99846","panchayatName":"Kuchhila"},{"name":"Bharhuli","code":"250665","panchayatCode":"99840","panchayatName":"Chittaini"},{"name":"Bharsara","code":"250760","panchayatCode":"99850","panchayatName":"Redia"},{"name":"Bharsaria","code":"250761","panchayatCode":"99850","panchayatName":"Redia"},{"name":"Bhunrwa","code":"250771","panchayatCode":"99849","panchayatName":"Nauwan"},{"name":"Bihar Dihra","code":"250784","panchayatCode":"99849","panchayatName":"Nauwan"},{"name":"Bijan Dehra","code":"250774","panchayatCode":"99848","panchayatName":"Narwar"},{"name":"Bindaulia","code":"250728","panchayatCode":"99838","panchayatName":"Balathari"},{"name":"Biranpur","code":"250805","panchayatCode":"99850","panchayatName":"Redia"},{"name":"Bisopur","code":"250752","panchayatCode":"99837","panchayatName":"Agarsi Dihra"},{"name":"Bohora","code":"250809","panchayatCode":"99839","panchayatName":"Chitawn"},{"name":"Chakia","code":"250624","panchayatCode":"99841","panchayatName":"Gara"},{"name":"Chakia","code":"250732","panchayatCode":"99841","panchayatName":"Gara"},{"name":"Chamraha","code":"250789","panchayatCode":"99849","panchayatName":"Nauwan"},{"name":"Charra Purwari","code":"250632","panchayatCode":"99846","panchayatName":"Kuchhila"},{"name":"Chatra Pachhimwari","code":"250622","panchayatCode":"99846","panchayatName":"Kuchhila"},{"name":"Chhitan Dehra","code":"250676","panchayatCode":"99840","panchayatName":"Chittaini"},{"name":"Chitaini","code":"250670","panchayatCode":"99840","panchayatName":"Chittaini"},{"name":"Chitawan","code":"250764","panchayatCode":"99839","panchayatName":"Chitawn"},{"name":"Damodar Dehra","code":"250639","panchayatCode":"99851","panchayatName":"Saraya"},{"name":"Damodardehra","code":"250743","panchayatCode":"99842","panchayatName":"Kanjar"},{"name":"Darhaon","code":"250796","panchayatCode":"99849","panchayatName":"Nauwan"},{"name":"Dayal Patti","code":"250667","panchayatCode":"99840","panchayatName":"Chittaini"},{"name":"Debaria","code":"250719","panchayatCode":"99847","panchayatName":"Laheri"},{"name":"Delha","code":"958683","panchayatCode":"","panchayatName":""},{"name":"Delhua","code":"250766","panchayatCode":"99839","panchayatName":"Chitawn"},{"name":"Deyadaha","code":"250790","panchayatCode":"99849","panchayatName":"Nauwan"},{"name":"Dhabchhua","code":"250772","panchayatCode":"99848","panchayatName":"Narwar"},{"name":"Dhanchhua","code":"250787","panchayatCode":"99849","panchayatName":"Nauwan"},{"name":"Dhantha","code":"250727","panchayatCode":"99838","panchayatName":"Balathari"},{"name":"Dharampura","code":"250641","panchayatCode":"99851","panchayatName":"Saraya"},{"name":"Dharmagatpur","code":"250655","panchayatCode":"99840","panchayatName":"Chittaini"},{"name":"Dighata","code":"250659","panchayatCode":"99840","panchayatName":"Chittaini"},{"name":"Doiya","code":"250803","panchayatCode":"99842","panchayatName":"Kanjar"},{"name":"Duja Ghewra","code":"250736","panchayatCode":"99842","panchayatName":"Kanjar"},{"name":"Dulla Saray","code":"250715","panchayatCode":"99837","panchayatName":"Agarsi Dihra"},{"name":"Ekauni","code":"250687","panchayatCode":"99840","panchayatName":"Chittaini"},{"name":"Ekauni","code":"250662","panchayatCode":"99844","panchayatName":"Kathrai"},{"name":"Ekaunia","code":"250748","panchayatCode":"99837","panchayatName":"Agarsi Dihra"},{"name":"Gajrarhi","code":"250731","panchayatCode":"99842","panchayatName":"Kanjar"},{"name":"Gangapur","code":"250657","panchayatCode":"99840","panchayatName":"Chittaini"},{"name":"Gara","code":"250629","panchayatCode":"99841","panchayatName":"Gara"},{"name":"Gaura","code":"250724","panchayatCode":"99838","panchayatName":"Balathari"},{"name":"Ghasa","code":"250801","panchayatCode":"99841","panchayatName":"Gara"},{"name":"Ghenwra","code":"250631","panchayatCode":"99846","panchayatName":"Kuchhila"},{"name":"Ghewra","code":"250740","panchayatCode":"99842","panchayatName":"Kanjar"},{"name":"Gobindpur","code":"250648","panchayatCode":"99851","panchayatName":"Saraya"},{"name":"Gongoulia","code":"250637","panchayatCode":"","panchayatName":""},{"name":"Hajapur","code":"958687","panchayatCode":"","panchayatName":""},{"name":"Hardaspur","code":"250775","panchayatCode":"99848","panchayatName":"Narwar"},{"name":"Harihar Dehra","code":"250635","panchayatCode":"99851","panchayatName":"Saraya"},{"name":"Harnathpur","code":"250649","panchayatCode":"99851","panchayatName":"Saraya"},{"name":"Harpur","code":"250663","panchayatCode":"99840","panchayatName":"Chittaini"},{"name":"Hatna","code":"250691","panchayatCode":"99843","panchayatName":"Kapasiya"},{"name":"Helha","code":"250770","panchayatCode":"99849","panchayatName":"Nauwan"},{"name":"Hetampur","code":"250725","panchayatCode":"99847","panchayatName":"Laheri"},{"name":"Hunrraha","code":"250800","panchayatCode":"99842","panchayatName":"Kanjar"},{"name":"Hurarha","code":"250646","panchayatCode":"","panchayatName":""},{"name":"Indapur","code":"250791","panchayatCode":"99849","panchayatName":"Nauwan"},{"name":"Jagdispur","code":"250638","panchayatCode":"99851","panchayatName":"Saraya"},{"name":"Jaiti Dihra","code":"250788","panchayatCode":"99848","panchayatName":"Narwar"},{"name":"Jalalpur","code":"250709","panchayatCode":"99843","panchayatName":"Kapasiya"},{"name":"Jhalkhoriya","code":"958682","panchayatCode":"","panchayatName":""},{"name":"Jharkhuria","code":"250754","panchayatCode":"99837","panchayatName":"Agarsi Dihra"},{"name":"Kaarmaini","code":"250755","panchayatCode":"99837","panchayatName":"Agarsi Dihra"},{"name":"Kapasia","code":"250703","panchayatCode":"99843","panchayatName":"Kapasiya"},{"name":"Karanchhata","code":"250692","panchayatCode":"99844","panchayatName":"Kathrai"},{"name":"Karbaniyan","code":"250804","panchayatCode":"99850","panchayatName":"Redia"},{"name":"Kariya","code":"958678","panchayatCode":"","panchayatName":""},{"name":"Karjar","code":"250738","panchayatCode":"99842","panchayatName":"Kanjar"},{"name":"Karmaini","code":"958671","panchayatCode":"","panchayatName":""},{"name":"Katharain","code":"250693","panchayatCode":"99844","panchayatName":"Kathrai"},{"name":"Katiyara","code":"250797","panchayatCode":"99839","panchayatName":"Chitawn"},{"name":"Khadawan","code":"250773","panchayatCode":"99848","panchayatName":"Narwar"},{"name":"Khaira","code":"250644","panchayatCode":"99847","panchayatName":"Laheri"},{"name":"Khairi","code":"250674","panchayatCode":"99848","panchayatName":"Narwar"},{"name":"Khairi","code":"250765","panchayatCode":"99840","panchayatName":"Chittaini"},{"name":"Khairi","code":"250786","panchayatCode":"99839","panchayatName":"Chitawn"},{"name":"Khairi","code":"250666","panchayatCode":"99840","panchayatName":"Chittaini"},{"name":"Khajapur","code":"250677","panchayatCode":"99840","panchayatName":"Chittaini"},{"name":"Khorhari","code":"250669","panchayatCode":"99840","panchayatName":"Chittaini"},{"name":"Khudas","code":"958681","panchayatCode":"","panchayatName":""},{"name":"Khudru","code":"250781","panchayatCode":"99848","panchayatName":"Narwar"},{"name":"Kochas","code":"950818","panchayatCode":"","panchayatName":""},{"name":"Kochas","code":"250726","panchayatCode":"","panchayatName":""},{"name":"Kohkar","code":"250712","panchayatCode":"99837","panchayatName":"Agarsi Dihra"},{"name":"Konharpurwa","code":"250778","panchayatCode":"99848","panchayatName":"Narwar"},{"name":"Korigawan","code":"250636","panchayatCode":"","panchayatName":""},{"name":"Korigawan","code":"950817","panchayatCode":"","panchayatName":""},{"name":"Kothuwa","code":"250750","panchayatCode":"99837","panchayatName":"Agarsi Dihra"},{"name":"Kuchhila","code":"250633","panchayatCode":"99846","panchayatName":"Kuchhila"},{"name":"Kursa","code":"250799","panchayatCode":"99842","panchayatName":"Kanjar"},{"name":"Kusahi","code":"250720","panchayatCode":"99847","panchayatName":"Laheri"},{"name":"Laheri","code":"250671","panchayatCode":"99847","panchayatName":"Laheri"},{"name":"Lakari","code":"250734","panchayatCode":"99838","panchayatName":"Balathari"},{"name":"Lakhanpura","code":"250699","panchayatCode":"99843","panchayatName":"Kapasiya"},{"name":"Latari","code":"250745","panchayatCode":"99850","panchayatName":"Redia"},{"name":"Latra","code":"250757","panchayatCode":"99850","panchayatName":"Redia"},{"name":"Lodipur","code":"250704","panchayatCode":"99843","panchayatName":"Kapasiya"},{"name":"Mahuari","code":"250708","panchayatCode":"99843","panchayatName":"Kapasiya"},{"name":"Majhauli","code":"250795","panchayatCode":"99849","panchayatName":"Nauwan"},{"name":"Mallu Dehra","code":"250642","panchayatCode":"99851","panchayatName":"Saraya"},{"name":"Mamrezpur","code":"250733","panchayatCode":"99838","panchayatName":"Balathari"},{"name":"Mandihra","code":"958685","panchayatCode":"","panchayatName":""},{"name":"Manipur","code":"250802","panchayatCode":"99842","panchayatName":"Kanjar"},{"name":"Manpura","code":"250705","panchayatCode":"99843","panchayatName":"Kapasiya"},{"name":"Mansapur","code":"250767","panchayatCode":"99839","panchayatName":"Chitawn"},{"name":"Marhuli","code":"958684","panchayatCode":"","panchayatName":""},{"name":"Maudehra","code":"250758","panchayatCode":"99850","panchayatName":"Redia"},{"name":"Meura","code":"250741","panchayatCode":"99842","panchayatName":"Kanjar"},{"name":"Mirga","code":"250623","panchayatCode":"99841","panchayatName":"Gara"},{"name":"Misir Potti","code":"250661","panchayatCode":"99840","panchayatName":"Chittaini"},{"name":"Misraulia","code":"250711","panchayatCode":"99837","panchayatName":"Agarsi Dihra"},{"name":"Mohanpur","code":"250710","panchayatCode":"99843","panchayatName":"Kapasiya"},{"name":"Nainakon","code":"250679","panchayatCode":"99840","panchayatName":"Chittaini"},{"name":"Narayanpur","code":"250729","panchayatCode":"99838","panchayatName":"Balathari"},{"name":"Narwar","code":"250780","panchayatCode":"99848","panchayatName":"Narwar"},{"name":"Naua","code":"250785","panchayatCode":"99849","panchayatName":"Nauwan"},{"name":"Navalia","code":"250656","panchayatCode":"99840","panchayatName":"Chittaini"},{"name":"Nimiyan","code":"250747","panchayatCode":"99837","panchayatName":"Agarsi Dihra"},{"name":"Ojhanwaliya","code":"958677","panchayatCode":"","panchayatName":""},{"name":"Pahanua","code":"250783","panchayatCode":"99849","panchayatName":"Nauwan"},{"name":"Pakari","code":"250735","panchayatCode":"99842","panchayatName":"Kanjar"},{"name":"Paltudehra","code":"250762","panchayatCode":"99850","panchayatName":"Redia"},{"name":"Panchu Dehri","code":"250810","panchayatCode":"99839","panchayatName":"Chitawn"},{"name":"Panditpura","code":"250625","panchayatCode":"99841","panchayatName":"Gara"},{"name":"Parasiya","code":"958670","panchayatCode":"","panchayatName":""},{"name":"Parmesardehra","code":"250737","panchayatCode":"99842","panchayatName":"Kanjar"},{"name":"Parmeshwar Dihra","code":"958672","panchayatCode":"","panchayatName":""},{"name":"Parsathua","code":"250685","panchayatCode":"99844","panchayatName":"Kathrai"},{"name":"Parsia","code":"250621","panchayatCode":"99846","panchayatName":"Kuchhila"},{"name":"Parsiya","code":"950702","panchayatCode":"","panchayatName":""},{"name":"Parsiya","code":"250723","panchayatCode":"99846","panchayatName":"Kuchhila"},{"name":"Patna","code":"250690","panchayatCode":"99843","panchayatName":"Kapasiya"},{"name":"Pauat","code":"250626","panchayatCode":"99841","panchayatName":"Gara"},{"name":"Petphorua","code":"250686","panchayatCode":"99844","panchayatName":"Kathrai"},{"name":"Phuli","code":"250653","panchayatCode":"99851","panchayatName":"Saraya"},{"name":"Phulwario","code":"250701","panchayatCode":"99843","panchayatName":"Kapasiya"},{"name":"Pithwaiya","code":"250807","panchayatCode":"99842","panchayatName":"Kanjar"},{"name":"Podumsi Dehra","code":"250643","panchayatCode":"99851","panchayatName":"Saraya"},{"name":"Purahra","code":"250756","panchayatCode":"99850","panchayatName":"Redia"},{"name":"Rajan Dih","code":"250650","panchayatCode":"99851","panchayatName":"Saraya"},{"name":"Rampur","code":"250718","panchayatCode":"99843","panchayatName":"Kapasiya"},{"name":"Raroser","code":"957590","panchayatCode":"","panchayatName":""},{"name":"Raroser","code":"957587","panchayatCode":"","panchayatName":""},{"name":"Redio","code":"957602","panchayatCode":"","panchayatName":""},{"name":"Redio","code":"957601","panchayatCode":"","panchayatName":""},{"name":"Reniya","code":"250744","panchayatCode":"99850","panchayatName":"Redia"},{"name":"Renria","code":"250658","panchayatCode":"99840","panchayatName":"Chittaini"},{"name":"Rupi","code":"250806","panchayatCode":"99850","panchayatName":"Redia"},{"name":"Rupinbandh","code":"250680","panchayatCode":"99840","panchayatName":"Chittaini"},{"name":"Sai","code":"250751","panchayatCode":"99837","panchayatName":"Agarsi Dihra"},{"name":"Salas","code":"250668","panchayatCode":"99840","panchayatName":"Chittaini"},{"name":"Sanwandehri","code":"250714","panchayatCode":"99837","panchayatName":"Agarsi Dihra"},{"name":"Sarangpur","code":"250634","panchayatCode":"99846","panchayatName":"Kuchhila"},{"name":"Sareya","code":"250652","panchayatCode":"99851","panchayatName":"Saraya"},{"name":"Saroser","code":"250782","panchayatCode":"99848","panchayatName":"Narwar"},{"name":"Satasa","code":"250716","panchayatCode":"99838","panchayatName":"Balathari"},{"name":"Semaria","code":"250647","panchayatCode":"99847","panchayatName":"Laheri"},{"name":"Shahpur","code":"250746","panchayatCode":"99850","panchayatName":"Redia"},{"name":"Shiwpur","code":"250627","panchayatCode":"99841","panchayatName":"Gara"},{"name":"Shiwpur","code":"250640","panchayatCode":"99841","panchayatName":"Gara"},{"name":"Sirpalpur","code":"250651","panchayatCode":"99851","panchayatName":"Saraya"},{"name":"Sobhalia","code":"250702","panchayatCode":"99843","panchayatName":"Kapasiya"},{"name":"Sobhipur","code":"250695","panchayatCode":"99844","panchayatName":"Kathrai"},{"name":"Sohasa","code":"250684","panchayatCode":"99844","panchayatName":"Kathrai"},{"name":"Sokrauli","code":"250694","panchayatCode":"99844","panchayatName":"Kathrai"},{"name":"Sorath","code":"250769","panchayatCode":"99849","panchayatName":"Nauwan"},{"name":"Sorathi","code":"250768","panchayatCode":"99839","panchayatName":"Chitawn"},{"name":"Sunderpur","code":"250706","panchayatCode":"99843","panchayatName":"Kapasiya"},{"name":"Tetaria","code":"250722","panchayatCode":"99847","panchayatName":"Laheri"},{"name":"Tirgunpur","code":"250696","panchayatCode":"99844","panchayatName":"Kathrai"},{"name":"Tirlokdehri","code":"250654","panchayatCode":"99851","panchayatName":"Saraya"},{"name":"Turkaha","code":"250749","panchayatCode":"99837","panchayatName":"Agarsi Dihra"},{"name":"Ubdhi","code":"250759","panchayatCode":"99850","panchayatName":"Redia"},{"name":"Usrawan","code":"250794","panchayatCode":"99849","panchayatName":"Nauwan"},{"name":"Usrawan","code":"250793","panchayatCode":"99849","panchayatName":"Nauwan"},{"name":"Vishopur","code":"958686","panchayatCode":"","panchayatName":""},{"name":"Wojhwalia","code":"950730","panchayatCode":"","panchayatName":""},{"name":"Wojhwalia","code":"250645","panchayatCode":"99851","panchayatName":"Saraya"}]