[{"name":"Adibatla","code":"574827","panchayatCode":"","panchayatName":""},{"name":"Alimiyakunta","code":"574842","panchayatCode":"210099","panchayatName":"Raipole"},{"name":"Bongloor","code":"574828","panchayatCode":"","panchayatName":""},{"name":"Cherla Patelguda","code":"912410","panchayatCode":"","panchayatName":""},{"name":"Chintapalleguda","code":"574829","panchayatCode":"","panchayatName":""},{"name":"Dandumailaram","code":"574836","panchayatCode":"210088","panchayatName":"Dandumailaram"},{"name":"Ferozguda","code":"574844","panchayatCode":"","panchayatName":""},{"name":"Ibrahimpatnam (Bagath) (Ct)","code":"574853","panchayatCode":"","panchayatName":""},{"name":"Ibrahimpatnam (Khalsa)","code":"574832","panchayatCode":"210105","panchayatName":"Uppariguda"},{"name":"Ismailshapampu","code":"574831","panchayatCode":"210099","panchayatName":"Raipole"},{"name":"Kappapahad","code":"574851","panchayatCode":"210090","panchayatName":"Kappapahad"},{"name":"Kongara Kalan","code":"574826","panchayatCode":"","panchayatName":""},{"name":"Mangalpalle","code":"574843","panchayatCode":"","panchayatName":""},{"name":"Muknoor","code":"574837","panchayatCode":"210093","panchayatName":"Mukunoor"},{"name":"Naganpalle","code":"574833","panchayatCode":"210094","panchayatName":"Naganpally"},{"name":"Narrepalle","code":"574835","panchayatCode":"210095","panchayatName":"Nerrepally"},{"name":"Pocharam","code":"574846","panchayatCode":"210097","panchayatName":"Pocharam"},{"name":"Polkampalle","code":"574834","panchayatCode":"210098","panchayatName":"Polkampally"},{"name":"Rainguda","code":"574838","panchayatCode":"210099","panchayatName":"Raipole"},{"name":"Raipole","code":"574840","panchayatCode":"210099","panchayatName":"Raipole"},{"name":"Ramdaspalle","code":"574830","panchayatCode":"","panchayatName":""},{"name":"Ramreddiguda","code":"574845","panchayatCode":"210097","panchayatName":"Pocharam"},{"name":"Tadlakalva","code":"574848","panchayatCode":"210106","panchayatName":"Yeliminedu"},{"name":"Tattikhana","code":"574841","panchayatCode":"210106","panchayatName":"Yeliminedu"},{"name":"Toolekalan","code":"574852","panchayatCode":"210104","panchayatName":"Tulekalan"},{"name":"Turkaguda","code":"574850","panchayatCode":"210103","panchayatName":"Thurkaguda"},{"name":"Uppariguda","code":"912411","panchayatCode":"","panchayatName":""},{"name":"Yeliminedu","code":"574847","panchayatCode":"210106","panchayatName":"Yeliminedu"},{"name":"Yengalaguda","code":"574839","panchayatCode":"210098","panchayatName":"Polkampally"},{"name":"Yerrakunta","code":"574849","panchayatCode":"210103","panchayatName":"Thurkaguda"}]