[{"name":"Amaiyasar","code":"354395","panchayatCode":"111565","panchayatName":"Rajpura"},{"name":"Ambabad","code":"354251","panchayatCode":"111555","panchayatName":"Daranga"},{"name":"Amdiha","code":"354346","panchayatCode":"111551","panchayatName":"Amdiha"},{"name":"Amjo","code":"354222","panchayatCode":"111567","panchayatName":"Tatkiyo Nawadih"},{"name":"Amjora","code":"354285","panchayatCode":"111558","panchayatName":"Husainabad"},{"name":"Anandpur","code":"354260","panchayatCode":"111560","panchayatName":"Jhhundi"},{"name":"Araria","code":"354282","panchayatCode":"111557","panchayatName":"Fulkari"},{"name":"Arenja","code":"354386","panchayatCode":"111552","panchayatName":"Baghmari"},{"name":"Asahna","code":"354375","panchayatCode":"111556","panchayatName":"Dhobana"},{"name":"Baghapathar","code":"354374","panchayatCode":"111556","panchayatName":"Dhobana"},{"name":"Baghmara","code":"354243","panchayatCode":"111567","panchayatName":"Tatkiyo Nawadih"},{"name":"Baghmari","code":"354379","panchayatCode":"111552","panchayatName":"Baghmari"},{"name":"Baghraidih","code":"354185","panchayatCode":"111553","panchayatName":"Barwan"},{"name":"Bahadurpur","code":"354219","panchayatCode":"111567","panchayatName":"Tatkiyo Nawadih"},{"name":"Bahrabank","code":"354250","panchayatCode":"111555","panchayatName":"Daranga"},{"name":"Baijnathpur","code":"354331","panchayatCode":"111563","panchayatName":"Mahuatand"},{"name":"Balampur","code":"354253","panchayatCode":"111555","panchayatName":"Daranga"},{"name":"Balnadi","code":"354348","panchayatCode":"111551","panchayatName":"Amdiha"},{"name":"Balraidih","code":"354195","panchayatCode":"111567","panchayatName":"Tatkiyo Nawadih"},{"name":"Balthar","code":"354409","panchayatCode":"111566","panchayatName":"Ramudih"},{"name":"Baltharwa","code":"354241","panchayatCode":"111567","panchayatName":"Tatkiyo Nawadih"},{"name":"Bandai","code":"354317","panchayatCode":"111562","panchayatName":"Kasathi"},{"name":"Bandar Basa","code":"354378","panchayatCode":"111552","panchayatName":"Baghmari"},{"name":"Bandgari","code":"354259","panchayatCode":"111560","panchayatName":"Jhhundi"},{"name":"Bangora","code":"354283","panchayatCode":"111557","panchayatName":"Fulkari"},{"name":"Bank Mundaria","code":"354329","panchayatCode":"111563","panchayatName":"Mahuatand"},{"name":"Banspahari","code":"354289","panchayatCode":"111564","panchayatName":"Manpur"},{"name":"Bara Minkhi","code":"354320","panchayatCode":"111562","panchayatName":"Kasathi"},{"name":"Baradbhura Pokhariya","code":"354326","panchayatCode":"111563","panchayatName":"Mahuatand"},{"name":"Barasoli","code":"354336","panchayatCode":"111563","panchayatName":"Mahuatand"},{"name":"Baratanr","code":"354293","panchayatCode":"111564","panchayatName":"Manpur"},{"name":"Bargunia","code":"354307","panchayatCode":"111564","panchayatName":"Manpur"},{"name":"Bariarpur","code":"354313","panchayatCode":"111562","panchayatName":"Kasathi"},{"name":"Bariyaradih","code":"354376","panchayatCode":"111556","panchayatName":"Dhobana"},{"name":"Barki Kharkhar","code":"354372","panchayatCode":"111556","panchayatName":"Dhobana"},{"name":"Barwan","code":"354198","panchayatCode":"111553","panchayatName":"Barwan"},{"name":"Barwatanr","code":"354217","panchayatCode":"111567","panchayatName":"Tatkiyo Nawadih"},{"name":"Basulia","code":"354216","panchayatCode":"111567","panchayatName":"Tatkiyo Nawadih"},{"name":"Baswaria","code":"354322","panchayatCode":"111562","panchayatName":"Kasathi"},{"name":"Behran","code":"354337","panchayatCode":"111563","panchayatName":"Mahuatand"},{"name":"Behran Chhit","code":"354339","panchayatCode":"111563","panchayatName":"Mahuatand"},{"name":"Belatikar","code":"354403","panchayatCode":"111559","panchayatName":"Jhhumarbad"},{"name":"Beltikri","code":"354315","panchayatCode":"111562","panchayatName":"Kasathi"},{"name":"Benidih","code":"354258","panchayatCode":"111560","panchayatName":"Jhhundi"},{"name":"Bermuka","code":"354208","panchayatCode":"111555","panchayatName":"Daranga"},{"name":"Bhagwanpur","code":"354194","panchayatCode":"111567","panchayatName":"Tatkiyo Nawadih"},{"name":"Bhaiaraydih","code":"354399","panchayatCode":"111559","panchayatName":"Jhhumarbad"},{"name":"Bhaisia","code":"354302","panchayatCode":"111564","panchayatName":"Manpur"},{"name":"Bhalpahri","code":"354230","panchayatCode":"111560","panchayatName":"Jhhundi"},{"name":"Bharthidih","code":"354277","panchayatCode":"111557","panchayatName":"Fulkari"},{"name":"Bhikhampur","code":"354349","panchayatCode":"111551","panchayatName":"Amdiha"},{"name":"Bhogtachhorat","code":"354335","panchayatCode":"111563","panchayatName":"Mahuatand"},{"name":"Bhojpur","code":"354423","panchayatCode":"111554","panchayatName":"Bhojpur"},{"name":"Bhugtabandh","code":"354433","panchayatCode":"111561","panchayatName":"Jitjorit"},{"name":"Bhuliamarni","code":"354224","panchayatCode":"111560","panchayatName":"Jhhundi"},{"name":"Birnia","code":"354377","panchayatCode":"111566","panchayatName":"Ramudih"},{"name":"Bisnathi","code":"354371","panchayatCode":"111556","panchayatName":"Dhobana"},{"name":"Buchi","code":"354311","panchayatCode":"111562","panchayatName":"Kasathi"},{"name":"Chaita","code":"354236","panchayatCode":"111560","panchayatName":"Jhhundi"},{"name":"Charakmara","code":"354261","panchayatCode":"111560","panchayatName":"Jhhundi"},{"name":"Chaudharidih","code":"354256","panchayatCode":"111560","panchayatName":"Jhhundi"},{"name":"Chaudharidih","code":"354356","panchayatCode":"111551","panchayatName":"Amdiha"},{"name":"Chhota Mirkhi","code":"354319","panchayatCode":"111562","panchayatName":"Kasathi"},{"name":"Chhota Rajasare","code":"354405","panchayatCode":"111559","panchayatName":"Jhhumarbad"},{"name":"Chhota Rosan","code":"354324","panchayatCode":"111563","panchayatName":"Mahuatand"},{"name":"Chitarmurgibad","code":"354413","panchayatCode":"111566","panchayatName":"Ramudih"},{"name":"Chitarmurgibad Chhit","code":"354408","panchayatCode":"111566","panchayatName":"Ramudih"},{"name":"Chitarpur","code":"354263","panchayatCode":"111560","panchayatName":"Jhhundi"},{"name":"Choto","code":"354434","panchayatCode":"111561","panchayatName":"Jitjorit"},{"name":"Daluraydih","code":"354384","panchayatCode":"111552","panchayatName":"Baghmari"},{"name":"Daranga","code":"354203","panchayatCode":"111555","panchayatName":"Daranga"},{"name":"Dewalpur","code":"354366","panchayatCode":"111559","panchayatName":"Jhhumarbad"},{"name":"Dhabwa","code":"354288","panchayatCode":"111564","panchayatName":"Manpur"},{"name":"Dhakdhaka","code":"354318","panchayatCode":"111562","panchayatName":"Kasathi"},{"name":"Dhanitanr","code":"354252","panchayatCode":"111555","panchayatName":"Daranga"},{"name":"Dharampur","code":"354358","panchayatCode":"111556","panchayatName":"Dhobana"},{"name":"Dharti Chak","code":"354410","panchayatCode":"111566","panchayatName":"Ramudih"},{"name":"Dhobna","code":"354370","panchayatCode":"111556","panchayatName":"Dhobana"},{"name":"Dhorsa","code":"354267","panchayatCode":"111558","panchayatName":"Husainabad"},{"name":"Dinajpur","code":"354388","panchayatCode":"111559","panchayatName":"Jhhumarbad"},{"name":"Domandih","code":"354257","panchayatCode":"111560","panchayatName":"Jhhundi"},{"name":"Dondia","code":"354309","panchayatCode":"111564","panchayatName":"Manpur"},{"name":"Duba","code":"354245","panchayatCode":"111555","panchayatName":"Daranga"},{"name":"Duba Nawadih","code":"354233","panchayatCode":"111560","panchayatName":"Jhhundi"},{"name":"Duhosuho","code":"354271","panchayatCode":"111558","panchayatName":"Husainabad"},{"name":"Dumar Kundi","code":"354381","panchayatCode":"111552","panchayatName":"Baghmari"},{"name":"Dumarjor","code":"354359","panchayatCode":"111556","panchayatName":"Dhobana"},{"name":"Durgiraidih","code":"354291","panchayatCode":"111564","panchayatName":"Manpur"},{"name":"Ektara","code":"354387","panchayatCode":"111559","panchayatName":"Jhhumarbad"},{"name":"Gajrajpur","code":"354367","panchayatCode":"111559","panchayatName":"Jhhumarbad"},{"name":"Gamardiha","code":"354415","panchayatCode":"111566","panchayatName":"Ramudih"},{"name":"Garbhusingha","code":"354246","panchayatCode":"111555","panchayatName":"Daranga"},{"name":"Ghaghi","code":"354373","panchayatCode":"111556","panchayatName":"Dhobana"},{"name":"Ghasko","code":"354343","panchayatCode":"111551","panchayatName":"Amdiha"},{"name":"Ghonghadih","code":"354350","panchayatCode":"111551","panchayatName":"Amdiha"},{"name":"Gidhaya","code":"354435","panchayatCode":"111561","panchayatName":"Jitjorit"},{"name":"Gobardaha","code":"354209","panchayatCode":"111553","panchayatName":"Barwan"},{"name":"Goithadih","code":"354353","panchayatCode":"111563","panchayatName":"Mahuatand"},{"name":"Gomdidih","code":"354360","panchayatCode":"111556","panchayatName":"Dhobana"},{"name":"Gosai Bandh","code":"354432","panchayatCode":"111561","panchayatName":"Jitjorit"},{"name":"Goslidih","code":"354188","panchayatCode":"111553","panchayatName":"Barwan"},{"name":"Hardiya","code":"354327","panchayatCode":"111563","panchayatName":"Mahuatand"},{"name":"Harodih","code":"354330","panchayatCode":"111563","panchayatName":"Mahuatand"},{"name":"Harokura","code":"354226","panchayatCode":"111560","panchayatName":"Jhhundi"},{"name":"Hathwari","code":"354347","panchayatCode":"111551","panchayatName":"Amdiha"},{"name":"Hethbargunia","code":"354316","panchayatCode":"111564","panchayatName":"Manpur"},{"name":"Hussainabad","code":"354272","panchayatCode":"111558","panchayatName":"Husainabad"},{"name":"Jagatpur","code":"354338","panchayatCode":"111563","panchayatName":"Mahuatand"},{"name":"Jagmaniya","code":"354357","panchayatCode":"111556","panchayatName":"Dhobana"},{"name":"Jagnadih","code":"354199","panchayatCode":"111553","panchayatName":"Barwan"},{"name":"Jamua","code":"354200","panchayatCode":"111553","panchayatName":"Barwan"},{"name":"Jamunia","code":"354286","panchayatCode":"111558","panchayatName":"Husainabad"},{"name":"Jaruadih","code":"354297","panchayatCode":"111564","panchayatName":"Manpur"},{"name":"Jasiadih","code":"354228","panchayatCode":"111560","panchayatName":"Jhhundi"},{"name":"Jhagrahi","code":"354345","panchayatCode":"111551","panchayatName":"Amdiha"},{"name":"Jhumarbad","code":"354391","panchayatCode":"111559","panchayatName":"Jhhumarbad"},{"name":"Jhuri","code":"354264","panchayatCode":"111560","panchayatName":"Jhhundi"},{"name":"Jigrachurat","code":"354436","panchayatCode":"111561","panchayatName":"Jitjorit"},{"name":"Jirwatanr","code":"354210","panchayatCode":"111553","panchayatName":"Barwan"},{"name":"Jitjori","code":"354427","panchayatCode":"111561","panchayatName":"Jitjorit"},{"name":"Jitkunda","code":"354197","panchayatCode":"111553","panchayatName":"Barwan"},{"name":"Jitpur","code":"354389","panchayatCode":"111559","panchayatName":"Jhhumarbad"},{"name":"Jorasimar","code":"354244","panchayatCode":"111555","panchayatName":"Daranga"},{"name":"Kamarsali","code":"354207","panchayatCode":"111555","panchayatName":"Daranga"},{"name":"Kapasia","code":"354411","panchayatCode":"111566","panchayatName":"Ramudih"},{"name":"Kapsa.","code":"354290","panchayatCode":"111551","panchayatName":"Amdiha"},{"name":"Kapsada","code":"354344","panchayatCode":"111564","panchayatName":"Manpur"},{"name":"Karanpura","code":"354306","panchayatCode":"111564","panchayatName":"Manpur"},{"name":"Karikado","code":"354299","panchayatCode":"111564","panchayatName":"Manpur"},{"name":"Karmatanr","code":"354223","panchayatCode":"111567","panchayatName":"Tatkiyo Nawadih"},{"name":"Kartorayadih","code":"354402","panchayatCode":"111559","panchayatName":"Jhhumarbad"},{"name":"Kasathi","code":"354314","panchayatCode":"111562","panchayatName":"Kasathi"},{"name":"Kasidih","code":"354255","panchayatCode":"111567","panchayatName":"Tatkiyo Nawadih"},{"name":"Kasuadih","code":"354214","panchayatCode":"111567","panchayatName":"Tatkiyo Nawadih"},{"name":"Kathghari","code":"354274","panchayatCode":"111557","panchayatName":"Fulkari"},{"name":"Kendua","code":"354393","panchayatCode":"111565","panchayatName":"Rajpura"},{"name":"Kewalpur","code":"354365","panchayatCode":"111559","panchayatName":"Jhhumarbad"},{"name":"Khamardih","code":"354361","panchayatCode":"111556","panchayatName":"Dhobana"},{"name":"Kharik","code":"354422","panchayatCode":"111554","panchayatName":"Bhojpur"},{"name":"Kharkuwan","code":"354425","panchayatCode":"111554","panchayatName":"Bhojpur"},{"name":"Kharna","code":"354431","panchayatCode":"111561","panchayatName":"Jitjorit"},{"name":"Kheruadih","code":"354240","panchayatCode":"111567","panchayatName":"Tatkiyo Nawadih"},{"name":"Kherwatari","code":"354437","panchayatCode":"111565","panchayatName":"Rajpura"},{"name":"Khijuria","code":"354187","panchayatCode":"111553","panchayatName":"Barwan"},{"name":"Khurrami","code":"354220","panchayatCode":"111567","panchayatName":"Tatkiyo Nawadih"},{"name":"Khutabandh","code":"354301","panchayatCode":"111564","panchayatName":"Manpur"},{"name":"Kinaidih","code":"354237","panchayatCode":"111560","panchayatName":"Jhhundi"},{"name":"Kokraha","code":"354400","panchayatCode":"111559","panchayatName":"Jhhumarbad"},{"name":"Kolharia","code":"354298","panchayatCode":"111557","panchayatName":"Fulkari"},{"name":"Kolharia","code":"354249","panchayatCode":"111555","panchayatName":"Daranga"},{"name":"Kolhariya","code":"354398","panchayatCode":"111559","panchayatName":"Jhhumarbad"},{"name":"Kuchiagarha","code":"354333","panchayatCode":"111563","panchayatName":"Mahuatand"},{"name":"Lalodih","code":"354191","panchayatCode":"111553","panchayatName":"Barwan"},{"name":"Lamba","code":"354211","panchayatCode":"111567","panchayatName":"Tatkiyo Nawadih"},{"name":"Lerwa","code":"354287","panchayatCode":"111558","panchayatName":"Husainabad"},{"name":"Lohari","code":"354429","panchayatCode":"111561","panchayatName":"Jitjorit"},{"name":"Madanpur","code":"354242","panchayatCode":"111567","panchayatName":"Tatkiyo Nawadih"},{"name":"Madhupur","code":"354363","panchayatCode":"111556","panchayatName":"Dhobana"},{"name":"Madhwadih","code":"354352","panchayatCode":"111551","panchayatName":"Amdiha"},{"name":"Mahbadia","code":"354340","panchayatCode":"111563","panchayatName":"Mahuatand"},{"name":"Majhidih","code":"354239","panchayatCode":"111567","panchayatName":"Tatkiyo Nawadih"},{"name":"Majhiladih","code":"354265","panchayatCode":"111558","panchayatName":"Husainabad"},{"name":"Majhiladih","code":"354303","panchayatCode":"111564","panchayatName":"Manpur"},{"name":"Majhlitanr","code":"354218","panchayatCode":"111567","panchayatName":"Tatkiyo Nawadih"},{"name":"Manda Mundi","code":"354438","panchayatCode":"111565","panchayatName":"Rajpura"},{"name":"Manguaknali","code":"354284","panchayatCode":"111557","panchayatName":"Fulkari"},{"name":"Maniyarpur","code":"354364","panchayatCode":"111559","panchayatName":"Jhhumarbad"},{"name":"Manpur","code":"354304","panchayatCode":"111564","panchayatName":"Manpur"},{"name":"Manusmari","code":"354325","panchayatCode":"111563","panchayatName":"Mahuatand"},{"name":"Mardandih","code":"354266","panchayatCode":"111558","panchayatName":"Husainabad"},{"name":"Markiari","code":"354354","panchayatCode":"111551","panchayatName":"Amdiha"},{"name":"Marro","code":"354279","panchayatCode":"111557","panchayatName":"Fulkari"},{"name":"Mathura Pokhar","code":"354416","panchayatCode":"111566","panchayatName":"Ramudih"},{"name":"Matkiya","code":"354390","panchayatCode":"111559","panchayatName":"Jhhumarbad"},{"name":"Moglasar","code":"354248","panchayatCode":"111555","panchayatName":"Daranga"},{"name":"Mohuatanr","code":"354332","panchayatCode":"111563","panchayatName":"Mahuatand"},{"name":"Muratari","code":"354215","panchayatCode":"111567","panchayatName":"Tatkiyo Nawadih"},{"name":"Naiadih","code":"354201","panchayatCode":"111553","panchayatName":"Barwan"},{"name":"Narainpur","code":"354268","panchayatCode":"111558","panchayatName":"Husainabad"},{"name":"Narha Simar","code":"354205","panchayatCode":"111555","panchayatName":"Daranga"},{"name":"Nauwadih","code":"354300","panchayatCode":"111557","panchayatName":"Fulkari"},{"name":"Nawadih","code":"354323","panchayatCode":"111563","panchayatName":"Mahuatand"},{"name":"Nawadih","code":"354341","panchayatCode":"111563","panchayatName":"Mahuatand"},{"name":"Nawadih","code":"354308","panchayatCode":"111564","panchayatName":"Manpur"},{"name":"Nawadih","code":"354229","panchayatCode":"111567","panchayatName":"Tatkiyo Nawadih"},{"name":"Nepodih","code":"354235","panchayatCode":"111560","panchayatName":"Jhhundi"},{"name":"Ojhadih","code":"354270","panchayatCode":"111558","panchayatName":"Husainabad"},{"name":"Pahariatanr","code":"354184","panchayatCode":"111553","panchayatName":"Barwan"},{"name":"Paharidih","code":"354426","panchayatCode":"111561","panchayatName":"Jitjorit"},{"name":"Paharidih","code":"354296","panchayatCode":"111564","panchayatName":"Manpur"},{"name":"Paharpur","code":"354321","panchayatCode":"111562","panchayatName":"Kasathi"},{"name":"Pahartali","code":"354312","panchayatCode":"111562","panchayatName":"Kasathi"},{"name":"Pahridih","code":"354221","panchayatCode":"111567","panchayatName":"Tatkiyo Nawadih"},{"name":"Paisarpur","code":"354397","panchayatCode":"111565","panchayatName":"Rajpura"},{"name":"Pandanbona","code":"354396","panchayatCode":"111565","panchayatName":"Rajpura"},{"name":"Panrjori","code":"354342","panchayatCode":"111563","panchayatName":"Mahuatand"},{"name":"Paran Dih Banusari Chhit","code":"354385","panchayatCode":"111552","panchayatName":"Baghmari"},{"name":"Parandih Banusari","code":"354380","panchayatCode":"111552","panchayatName":"Baghmari"},{"name":"Pararia","code":"354305","panchayatCode":"111564","panchayatName":"Manpur"},{"name":"Parsbani","code":"354227","panchayatCode":"111560","panchayatName":"Jhhundi"},{"name":"Paruraydih","code":"354404","panchayatCode":"111552","panchayatName":"Baghmari"},{"name":"Patharchapti","code":"354424","panchayatCode":"111554","panchayatName":"Bhojpur"},{"name":"Pathria","code":"354212","panchayatCode":"111553","panchayatName":"Barwan"},{"name":"Patopahri","code":"354280","panchayatCode":"111557","panchayatName":"Fulkari"},{"name":"Phulkari","code":"354275","panchayatCode":"111557","panchayatName":"Fulkari"},{"name":"Phutabandh","code":"354262","panchayatCode":"111560","panchayatName":"Jhhundi"},{"name":"Pindari","code":"354206","panchayatCode":"111555","panchayatName":"Daranga"},{"name":"Piparbadiya","code":"354441","panchayatCode":"111561","panchayatName":"Jitjorit"},{"name":"Pipra","code":"354292","panchayatCode":"111557","panchayatName":"Fulkari"},{"name":"Pipratol","code":"354192","panchayatCode":"111553","panchayatName":"Barwan"},{"name":"Pirhakata","code":"354394","panchayatCode":"111565","panchayatName":"Rajpura"},{"name":"Purenia","code":"354278","panchayatCode":"111557","panchayatName":"Fulkari"},{"name":"Purnadih","code":"354430","panchayatCode":"111561","panchayatName":"Jitjorit"},{"name":"Putarjor","code":"354202","panchayatCode":"111553","panchayatName":"Barwan"},{"name":"Raghunathpur","code":"354414","panchayatCode":"111566","panchayatName":"Ramudih"},{"name":"Rajji","code":"354193","panchayatCode":"111553","panchayatName":"Barwan"},{"name":"Rajpura","code":"354213","panchayatCode":"111567","panchayatName":"Tatkiyo Nawadih"},{"name":"Rajpura","code":"354392","panchayatCode":"111565","panchayatName":"Rajpura"},{"name":"Rampur","code":"354407","panchayatCode":"111561","panchayatName":"Jitjorit"},{"name":"Ramraidih","code":"354355","panchayatCode":"111551","panchayatName":"Amdiha"},{"name":"Ramsagar","code":"354420","panchayatCode":"111566","panchayatName":"Ramudih"},{"name":"Ramudih","code":"354417","panchayatCode":"111566","panchayatName":"Ramudih"},{"name":"Rangniatanr","code":"354186","panchayatCode":"111553","panchayatName":"Barwan"},{"name":"Ratanbad","code":"354231","panchayatCode":"111560","panchayatName":"Jhhundi"},{"name":"Rautdih","code":"354273","panchayatCode":"111558","panchayatName":"Husainabad"},{"name":"Riguamarni","code":"354189","panchayatCode":"111553","panchayatName":"Barwan"},{"name":"Sadhwadih","code":"354276","panchayatCode":"111560","panchayatName":"Jhhundi"},{"name":"Saerjangal","code":"354295","panchayatCode":"111564","panchayatName":"Manpur"},{"name":"Saharpura","code":"354225","panchayatCode":"111560","panchayatName":"Jhhundi"},{"name":"Samaiatanr","code":"354238","panchayatCode":"111560","panchayatName":"Jhhundi"},{"name":"Samlapur","code":"354269","panchayatCode":"111558","panchayatName":"Husainabad"},{"name":"Sankarpur","code":"354421","panchayatCode":"111561","panchayatName":"Jitjorit"},{"name":"Saptabandh","code":"354281","panchayatCode":"111557","panchayatName":"Fulkari"},{"name":"Sardaha","code":"354412","panchayatCode":"111552","panchayatName":"Baghmari"},{"name":"Saruka","code":"354368","panchayatCode":"111556","panchayatName":"Dhobana"},{"name":"Semra Khas","code":"354382","panchayatCode":"111552","panchayatName":"Baghmari"},{"name":"Semradih","code":"354383","panchayatCode":"111552","panchayatName":"Baghmari"},{"name":"Simrapoj","code":"354401","panchayatCode":"111559","panchayatName":"Jhhumarbad"},{"name":"Siri","code":"354204","panchayatCode":"111555","panchayatName":"Daranga"},{"name":"Sirsia","code":"354439","panchayatCode":"111565","panchayatName":"Rajpura"},{"name":"Sirsia Chhit","code":"354428","panchayatCode":"111561","panchayatName":"Jitjorit"},{"name":"Sirsia Chhit","code":"354442","panchayatCode":"111561","panchayatName":"Jitjorit"},{"name":"Siwsagar","code":"354328","panchayatCode":"111563","panchayatName":"Mahuatand"},{"name":"Sultanpur","code":"354419","panchayatCode":"111566","panchayatName":"Ramudih"},{"name":"Sundardih","code":"354190","panchayatCode":"111553","panchayatName":"Barwan"},{"name":"Suriya Bandh","code":"354440","panchayatCode":"111561","panchayatName":"Jitjorit"},{"name":"Tatkio","code":"354196","panchayatCode":"111567","panchayatName":"Tatkiyo Nawadih"},{"name":"Thakuria Pahari","code":"354232","panchayatCode":"111560","panchayatName":"Jhhundi"},{"name":"Thariyari","code":"354362","panchayatCode":"111556","panchayatName":"Dhobana"},{"name":"Thuthamarni","code":"354369","panchayatCode":"111556","panchayatName":"Dhobana"},{"name":"Tilauna","code":"354234","panchayatCode":"111560","panchayatName":"Jhhundi"},{"name":"Tiljori","code":"354418","panchayatCode":"111554","panchayatName":"Bhojpur"},{"name":"Tilokitanr","code":"354254","panchayatCode":"111555","panchayatName":"Daranga"},{"name":"Titichapar","code":"354334","panchayatCode":"111563","panchayatName":"Mahuatand"},{"name":"Toombo","code":"354247","panchayatCode":"111555","panchayatName":"Daranga"},{"name":"Udhwadih","code":"354351","panchayatCode":"111551","panchayatName":"Amdiha"},{"name":"Ujanpur","code":"354294","panchayatCode":"111564","panchayatName":"Manpur"},{"name":"Upardih","code":"354310","panchayatCode":"111564","panchayatName":"Manpur"},{"name":"Utimpur","code":"354406","panchayatCode":"111561","panchayatName":"Jitjorit"}]