[{"name":"Amarpura","code":"102298","panchayatCode":"40229","panchayatName":"Kudaila"},{"name":"Amrit Kheri","code":"102320","panchayatCode":"40231","panchayatName":"Lahariya"},{"name":"Aranya Kalan","code":"102326","panchayatCode":"40211","panchayatName":"Arniya Kalan"},{"name":"Aranya Khurd","code":"102301","panchayatCode":"40211","panchayatName":"Arniya Kalan"},{"name":"Banda","code":"102310","panchayatCode":"40244","panchayatName":"Undwa"},{"name":"Bansya Heri","code":"102304","panchayatCode":"40211","panchayatName":"Arniya Kalan"},{"name":"Barodiya Antari","code":"102272","panchayatCode":"40239","panchayatName":"Salawad Khurd"},{"name":"Beed Mandi","code":"102274","panchayatCode":"40230","panchayatName":"Lakshmipura"},{"name":"Bhaopura","code":"102309","panchayatCode":"40216","panchayatName":"Devli Khurd"},{"name":"Bheempura","code":"102282","panchayatCode":"40220","panchayatName":"Goyanda"},{"name":"Bishanya Kheri","code":"102296","panchayatCode":"40216","panchayatName":"Devli Khurd"},{"name":"Budhkhan","code":"102267","panchayatCode":"40213","panchayatName":"Budhkhan"},{"name":"Burankheri","code":"102287","panchayatCode":"40220","panchayatName":"Goyanda"},{"name":"Chhatrapura","code":"102277","panchayatCode":"40237","panchayatName":"Richadiya"},{"name":"Dariya","code":"102284","panchayatCode":"40237","panchayatName":"Richadiya"},{"name":"Deoli Khurd","code":"102308","panchayatCode":"40216","panchayatName":"Devli Khurd"},{"name":"Devipura","code":"102285","panchayatCode":"40237","panchayatName":"Richadiya"},{"name":"Dhakya","code":"102232","panchayatCode":"40237","panchayatName":"Richadiya"},{"name":"Dharnawad","code":"102314","panchayatCode":"40217","panchayatName":"Dharnawad"},{"name":"Dingasi","code":"102266","panchayatCode":"40239","panchayatName":"Salawad Khurd"},{"name":"Dod Kheri","code":"102311","panchayatCode":"40233","panchayatName":"Manda"},{"name":"Durjanpura","code":"102299","panchayatCode":"40230","panchayatName":"Lakshmipura"},{"name":"Durkali","code":"102283","panchayatCode":"40237","panchayatName":"Richadiya"},{"name":"Gadiya","code":"102325","panchayatCode":"40218","panchayatName":"Gadiya"},{"name":"Gaupura","code":"102270","panchayatCode":"40239","panchayatName":"Salawad Khurd"},{"name":"Gola","code":"102327","panchayatCode":"40211","panchayatName":"Arniya Kalan"},{"name":"Gordhanpura","code":"955581","panchayatCode":"","panchayatName":""},{"name":"Goyanda","code":"102288","panchayatCode":"40220","panchayatName":"Goyanda"},{"name":"Hanotya","code":"102324","panchayatCode":"40218","panchayatName":"Gadiya"},{"name":"Hanuvantkhera","code":"955583","panchayatCode":"","panchayatName":""},{"name":"Haripura","code":"102318","panchayatCode":"40216","panchayatName":"Devli Khurd"},{"name":"Hemal Kheri","code":"102317","panchayatCode":"40217","panchayatName":"Dharnawad"},{"name":"Jagpura","code":"102315","panchayatCode":"40217","panchayatName":"Dharnawad"},{"name":"Jhilara","code":"102271","panchayatCode":"40239","panchayatName":"Salawad Khurd"},{"name":"Jhiri","code":"102269","panchayatCode":"40239","panchayatName":"Salawad Khurd"},{"name":"Julmi","code":"102319","panchayatCode":"40223","panchayatName":"Jhulmi"},{"name":"Khairabad (Ct)","code":"102331","panchayatCode":"40224","panchayatName":"Khairabad"},{"name":"Kishorpura","code":"102295","panchayatCode":"40233","panchayatName":"Manda"},{"name":"Kola","code":"102321","panchayatCode":"40218","panchayatName":"Gadiya"},{"name":"Kudayla","code":"102276","panchayatCode":"40229","panchayatName":"Kudaila"},{"name":"Kumbhkot (Ct)","code":"102335","panchayatCode":"244177","panchayatName":"Kumbhkot"},{"name":"Kutkya","code":"102263","panchayatCode":"40235","panchayatName":"Peepa Kheri"},{"name":"Lakhariya","code":"102322","panchayatCode":"40231","panchayatName":"Lahariya"},{"name":"Lasoriya","code":"102289","panchayatCode":"40220","panchayatName":"Goyanda"},{"name":"Laxmipura","code":"102300","panchayatCode":"40230","panchayatName":"Lakshmipura"},{"name":"Manda","code":"102292","panchayatCode":"40233","panchayatName":"Manda"},{"name":"Mandali","code":"102293","panchayatCode":"40233","panchayatName":"Manda"},{"name":"Mandi Nathan","code":"102302","panchayatCode":"40230","panchayatName":"Lakshmipura"},{"name":"Mandi Veeran","code":"102328","panchayatCode":"40218","panchayatName":"Gadiya"},{"name":"Mayla","code":"102275","panchayatCode":"40229","panchayatName":"Kudaila"},{"name":"Moondiya","code":"102290","panchayatCode":"40220","panchayatName":"Goyanda"},{"name":"Nalodiya","code":"102307","panchayatCode":"40231","panchayatName":"Lahariya"},{"name":"Nimana","code":"102256","panchayatCode":"40235","panchayatName":"Peepa Kheri"},{"name":"Nyamat Kheri","code":"102313","panchayatCode":"40217","panchayatName":"Dharnawad"},{"name":"Pama Kheri","code":"102262","panchayatCode":"40235","panchayatName":"Peepa Kheri"},{"name":"Payli","code":"102303","panchayatCode":"40211","panchayatName":"Arniya Kalan"},{"name":"Peepa Kheri","code":"102259","panchayatCode":"40239","panchayatName":"Salawad Khurd"},{"name":"Rampura","code":"102264","panchayatCode":"40239","panchayatName":"Salawad Khurd"},{"name":"Rawali","code":"102294","panchayatCode":"40233","panchayatName":"Manda"},{"name":"Richadiya","code":"102286","panchayatCode":"40237","panchayatName":"Richadiya"},{"name":"Roshli","code":"955614","panchayatCode":"","panchayatName":""},{"name":"Salawad Kalan","code":"102273","panchayatCode":"40239","panchayatName":"Salawad Khurd"},{"name":"Salawad Khurd","code":"102268","panchayatCode":"40239","panchayatName":"Salawad Khurd"},{"name":"San Khera","code":"102291","panchayatCode":"40233","panchayatName":"Manda"},{"name":"Sandpur","code":"102297","panchayatCode":"40229","panchayatName":"Kudaila"},{"name":"Satalkheri (Ct)","code":"102333","panchayatCode":"40241","panchayatName":"Satal Kheri"},{"name":"Semalkheri","code":"102305","panchayatCode":"40231","panchayatName":"Lahariya"},{"name":"Suket","code":"955548","panchayatCode":"","panchayatName":""},{"name":"Suket (Ct)","code":"102334","panchayatCode":"","panchayatName":""},{"name":"Surera","code":"102306","panchayatCode":"40211","panchayatName":"Arniya Kalan"},{"name":"Tamoliya","code":"102278","panchayatCode":"40237","panchayatName":"Richadiya"},{"name":"Teen Tapri","code":"952052","panchayatCode":"","panchayatName":""},{"name":"Teen Tapri","code":"949289","panchayatCode":"","panchayatName":""},{"name":"Telya Kheri","code":"102316","panchayatCode":"40238","panchayatName":"Saharawda"},{"name":"Udpura","code":"102323","panchayatCode":"40218","panchayatName":"Gadiya"},{"name":"Ummedpura","code":"102265","panchayatCode":"40239","panchayatName":"Salawad Khurd"},{"name":"Undwa","code":"102312","panchayatCode":"40244","panchayatName":"Undwa"}]