[{"name":"Agar Laga Gawali","code":"41971","panchayatCode":"22185","panchayatName":"Aagar"},{"name":"Agar Laga Jinagor","code":"41973","panchayatCode":"22185","panchayatName":"Aagar"},{"name":"Akshawara","code":"41959","panchayatCode":"22235","panchayatName":"Lakheri"},{"name":"Andrapa","code":"41919","panchayatCode":"22188","panchayatName":"Andrapa"},{"name":"Bacchuwa Ban Malla","code":"42025","panchayatCode":"22269","panchayatName":"Vachhuwa Wan"},{"name":"Bacchuwa Ban Talla","code":"42045","panchayatCode":"259848","panchayatName":"Vachuwawan Talla"},{"name":"Badiya Sem","code":"41988","panchayatCode":"22261","panchayatName":"Silanga"},{"name":"Bajyani","code":"41964","panchayatCode":"22191","panchayatName":"Baniyani"},{"name":"Banjyani","code":"42018","panchayatCode":"22215","panchayatName":"Jalchaura Malla"},{"name":"Bausar","code":"41942","panchayatCode":"","panchayatName":""},{"name":"Bhains Wara Sain","code":"41920","panchayatCode":"22252","panchayatName":"Parwari"},{"name":"Bhandari Khor","code":"41999","panchayatCode":"22195","panchayatName":"Bhandari Khor"},{"name":"Bhanot Gwar","code":"41980","panchayatCode":"22246","panchayatName":"Mehal Chauri"},{"name":"Bheriyana Laga Lakheri","code":"41961","panchayatCode":"243039","panchayatName":"Bhatiyana"},{"name":"Bina","code":"41966","panchayatCode":"22270","panchayatName":"Veena"},{"name":"Bisara Khet Urf Harsari","code":"41987","panchayatCode":"22246","panchayatName":"Mehal Chauri"},{"name":"Bisarakheta Palla","code":"41979","panchayatCode":"22246","panchayatName":"Mehal Chauri"},{"name":"Bukhara Kheta","code":"41998","panchayatCode":"22195","panchayatName":"Bhandari Khor"},{"name":"Chhapali","code":"41907","panchayatCode":"22256","panchayatName":"Ramra Malla"},{"name":"Chhari Sain","code":"41955","panchayatCode":"243036","panchayatName":"Chhadisen"},{"name":"Chhasiya Kot","code":"42007","panchayatCode":"22195","panchayatName":"Bhandari Khor"},{"name":"Chhina Kulari","code":"41890","panchayatCode":"22207","panchayatName":"Gandiyal Malla"},{"name":"Chorda","code":"41883","panchayatCode":"22199","panchayatName":"Chorda"},{"name":"Dadeo Laga Panchali","code":"41945","panchayatCode":"22250","panchayatName":"Panchali"},{"name":"Dadiyalgaon Basisen","code":"41958","panchayatCode":"22231","panchayatName":"Koylakh"},{"name":"Danga Laga Pajyana","code":"41917","panchayatCode":"22204","panchayatName":"Dungri"},{"name":"Dasamiya Gaon","code":"42046","panchayatCode":"22217","panchayatName":"Jhumakhet Uttari"},{"name":"Devpuri","code":"42021","panchayatCode":"22200","panchayatName":"Devpuri"},{"name":"Dewalgarh","code":"42024","panchayatCode":"22203","panchayatName":"Diwadhar"},{"name":"Dewali Jangal","code":"42019","panchayatCode":"22200","panchayatName":"Devpuri"},{"name":"Dham Dev","code":"42041","panchayatCode":"22229","panchayatName":"Kot"},{"name":"Dhargair","code":"41939","panchayatCode":"","panchayatName":""},{"name":"Dhargar","code":"41985","panchayatCode":"22246","panchayatName":"Mehal Chauri"},{"name":"Divadhar","code":"42028","panchayatCode":"22203","panchayatName":"Diwadhar"},{"name":"Dobiya Tal","code":"42034","panchayatCode":"293871","panchayatName":"Sera"},{"name":"Dubtoli Sunargwad","code":"942216","panchayatCode":"","panchayatName":""},{"name":"Dugara Laga Sahankot","code":"41997","panchayatCode":"22195","panchayatName":"Bhandari Khor"},{"name":"Dungri","code":"41918","panchayatCode":"22204","panchayatName":"Dungri"},{"name":"Farakande Talli","code":"41900","panchayatCode":"22205","panchayatName":"Farkande"},{"name":"Farkande Malli","code":"41899","panchayatCode":"22205","panchayatName":"Farkande"},{"name":"Farson","code":"41976","panchayatCode":"22185","panchayatName":"Aagar"},{"name":"Gadauta","code":"42031","panchayatCode":"22242","panchayatName":"Malkot"},{"name":"Gadoli","code":"41937","panchayatCode":"","panchayatName":""},{"name":"Gair","code":"41930","panchayatCode":"","panchayatName":""},{"name":"Ganwali","code":"41924","panchayatCode":"","panchayatName":""},{"name":"Garolitalli","code":"42053","panchayatCode":"22377","panchayatName":"Chamola"},{"name":"Gaul","code":"41954","panchayatCode":"22211","panchayatName":"Gol"},{"name":"Ghandiyal Khalsa Laga Chapal","code":"41903","panchayatCode":"22207","panchayatName":"Gandiyal Malla"},{"name":"Ghandiyal Lagga Chhapali","code":"41904","panchayatCode":"22209","panchayatName":"Ghandiyal"},{"name":"Ghuma Khet Malla","code":"42044","panchayatCode":"22216","panchayatName":"Jhumakhet"},{"name":"Gogana Malla","code":"42010","panchayatCode":"22210","panchayatName":"Gogna Malla"},{"name":"Gogana Talla","code":"42011","panchayatCode":"22210","panchayatName":"Gogna Malla"},{"name":"Gwar","code":"41932","panchayatCode":"","panchayatName":""},{"name":"Haragarh","code":"41969","panchayatCode":"22213","panchayatName":"Hargarh"},{"name":"Hargarh Laga Jaugrh","code":"41967","panchayatCode":"22270","panchayatName":"Veena"},{"name":"Hislani","code":"41994","panchayatCode":"22221","panchayatName":"Kalyani Talli"},{"name":"Hulan Kot Walla","code":"41990","panchayatCode":"22246","panchayatName":"Mehal Chauri"},{"name":"Hularkot Palla","code":"41991","panchayatCode":"22246","panchayatName":"Mehal Chauri"},{"name":"Jaitoli Laga Gwar","code":"41933","panchayatCode":"","panchayatName":""},{"name":"Jalchaura","code":"936721","panchayatCode":"","panchayatName":""},{"name":"Jaul Chaura Malla","code":"42023","panchayatCode":"22215","panchayatName":"Jalchaura Malla"},{"name":"Jaul Chaura Talla","code":"42015","panchayatCode":"22203","panchayatName":"Diwadhar"},{"name":"Jhuma Khet Talla","code":"42047","panchayatCode":"22216","panchayatName":"Jhumakhet"},{"name":"Jinagor","code":"41977","panchayatCode":"259852","panchayatName":"Jingore"},{"name":"Jwalagiri Kalyan","code":"42002","panchayatCode":"22221","panchayatName":"Kalyani Talli"},{"name":"Kalchunda","code":"42027","panchayatCode":"22219","panchayatName":"Kalchunda"},{"name":"Kali Mati","code":"42035","panchayatCode":"22220","panchayatName":"Kalimati"},{"name":"Kalu Bisht Sera","code":"42026","panchayatCode":"259848","panchayatName":"Vachuwawan Talla"},{"name":"Kalyana Malla (Lali Kalyani)","code":"41995","panchayatCode":"22221","panchayatName":"Kalyani Talli"},{"name":"Kalyana Talla","code":"42000","panchayatCode":"22221","panchayatName":"Kalyani Talli"},{"name":"Kamand","code":"41923","panchayatCode":"22204","panchayatName":"Dungri"},{"name":"Kandari Khor","code":"42017","panchayatCode":"22222","panchayatName":"Kandari Khor"},{"name":"Khadun Laga Gawali","code":"41925","panchayatCode":"22204","panchayatName":"Dungri"},{"name":"Khan Gwar Sera","code":"41892","panchayatCode":"22205","panchayatName":"Farkande"},{"name":"Khatriyana","code":"41940","panchayatCode":"","panchayatName":""},{"name":"Khinsar","code":"41992","panchayatCode":"22238","panchayatName":"Maikholi"},{"name":"Kolakhi Gwar","code":"41975","panchayatCode":"22246","panchayatName":"Mehal Chauri"},{"name":"Kolani","code":"42042","panchayatCode":"22228","panchayatName":"Kolani"},{"name":"Koli Mali","code":"42052","panchayatCode":"22375","panchayatName":"Bhatoli Laga Gairoli"},{"name":"Koliyana Laga Dhargair","code":"41929","panchayatCode":"","panchayatName":""},{"name":"Kot","code":"42040","panchayatCode":"22229","panchayatName":"Kot"},{"name":"Kotha","code":"42003","panchayatCode":"22230","panchayatName":"Kota"},{"name":"Kothar","code":"41922","panchayatCode":"22204","panchayatName":"Dungri"},{"name":"Kulagar","code":"41908","panchayatCode":"22188","panchayatName":"Andrapa"},{"name":"Kumeli Laga Saliyana","code":"41927","panchayatCode":"","panchayatName":""},{"name":"Kumoli Raiwan","code":"41912","panchayatCode":"259851","panchayatName":"Nail Lagga Farkande"},{"name":"Kunakhet","code":"41965","panchayatCode":"22233","panchayatName":"Kunkhet"},{"name":"Kuneli Laga Marora","code":"41896","panchayatCode":"22244","panchayatName":"Maroda"},{"name":"Kunigar Bichli","code":"42004","panchayatCode":"22232","panchayatName":"Kunigad Malli"},{"name":"Kunigar Malli","code":"42001","panchayatCode":"22232","panchayatName":"Kunigad Malli"},{"name":"Kunigar Talli","code":"42009","panchayatCode":"22195","panchayatName":"Bhandari Khor"},{"name":"Kushrani Bichali","code":"42043","panchayatCode":"259849","panchayatName":"Kusrani Talli"},{"name":"Kushrani Malli","code":"42050","panchayatCode":"22234","panchayatName":"Kusrani"},{"name":"Kushrani Talli","code":"42048","panchayatCode":"259849","panchayatName":"Kusrani Talli"},{"name":"Kwilakh","code":"41957","panchayatCode":"22231","panchayatName":"Koylakh"},{"name":"Lakhan","code":"42020","panchayatCode":"22200","panchayatName":"Devpuri"},{"name":"Lakheri","code":"41960","panchayatCode":"22235","panchayatName":"Lakheri"},{"name":"Lam Bagar","code":"42051","panchayatCode":"22236","panchayatName":"Lambagar"},{"name":"Latu Gair","code":"42036","panchayatCode":"22242","panchayatName":"Malkot"},{"name":"Latudhar","code":"41978","panchayatCode":"243032","panchayatName":"Ramda Talla"},{"name":"Maikholi","code":"41986","panchayatCode":"22238","panchayatName":"Maikholi"},{"name":"Majerasar","code":"41905","panchayatCode":"22207","panchayatName":"Gandiyal Malla"},{"name":"Malkot","code":"42030","panchayatCode":"22242","panchayatName":"Malkot"},{"name":"Manda Laga Siman","code":"41947","panchayatCode":"22265","panchayatName":"Sumerpur"},{"name":"Marora","code":"41897","panchayatCode":"22244","panchayatName":"Maroda"},{"name":"Maso Sera","code":"41963","panchayatCode":"243039","panchayatName":"Bhatiyana"},{"name":"Mathakot","code":"41916","panchayatCode":"22245","panchayatName":"Mathkot"},{"name":"Mathkot Khal","code":"41915","panchayatCode":"22245","panchayatName":"Mathkot"},{"name":"Mehal Chauri","code":"41983","panchayatCode":"22246","panchayatName":"Mehal Chauri"},{"name":"Mehargaon","code":"41910","panchayatCode":"22256","panchayatName":"Ramra Malla"},{"name":"Melbagar","code":"41901","panchayatCode":"22209","panchayatName":"Ghandiyal"},{"name":"Morpani","code":"41996","panchayatCode":"22221","panchayatName":"Kalyani Talli"},{"name":"Muson","code":"41944","panchayatCode":"243037","panchayatName":"Moonson"},{"name":"Nail","code":"42022","panchayatCode":"22248","panchayatName":"Nail"},{"name":"Nail Laga Farakande","code":"41911","panchayatCode":"259851","panchayatName":"Nail Lagga Farkande"},{"name":"Naini","code":"42039","panchayatCode":"22249","panchayatName":"Naini"},{"name":"Naugadh Dhal Kandae","code":"41914","panchayatCode":"22251","panchayatName":"Panjyana"},{"name":"Naugaon Malla","code":"41952","panchayatCode":"243037","panchayatName":"Moonson"},{"name":"Naugaon Talla","code":"42037","panchayatCode":"22228","panchayatName":"Kolani"},{"name":"Nigal Sain","code":"41931","panchayatCode":"259847","panchayatName":"Sintoli"},{"name":"Pajai Sera","code":"41921","panchayatCode":"22204","panchayatName":"Dungri"},{"name":"Pajyana","code":"41913","panchayatCode":"22251","panchayatName":"Panjyana"},{"name":"Pala Bagar","code":"42014","panchayatCode":"22268","panchayatName":"Teituda"},{"name":"Panchali","code":"41951","panchayatCode":"22250","panchayatName":"Panchali"},{"name":"Paramghat Laga Chhapali","code":"41906","panchayatCode":"22207","panchayatName":"Gandiyal Malla"},{"name":"Parawari","code":"41894","panchayatCode":"22252","panchayatName":"Parwari"},{"name":"Pata Bungi","code":"42012","panchayatCode":"22242","panchayatName":"Malkot"},{"name":"Patal Chaura","code":"41953","panchayatCode":"22231","panchayatName":"Koylakh"},{"name":"Pitoti Lagga Gain","code":"41934","panchayatCode":"","panchayatName":""},{"name":"Ramara Malla","code":"41891","panchayatCode":"22256","panchayatName":"Ramra Malla"},{"name":"Ramara Talla","code":"41970","panchayatCode":"243032","panchayatName":"Ramda Talla"},{"name":"Rangchaura","code":"41993","panchayatCode":"243040","panchayatName":"Rangchauda"},{"name":"Rikholi","code":"41926","panchayatCode":"","panchayatName":""},{"name":"Rithiya","code":"41935","panchayatCode":"259847","panchayatName":"Sintoli"},{"name":"Rohira","code":"41962","panchayatCode":"22258","panchayatName":"Rohida"},{"name":"Roykot","code":"42032","panchayatCode":"22242","panchayatName":"Malkot"},{"name":"Ruriya Tal","code":"41902","panchayatCode":"22209","panchayatName":"Ghandiyal"},{"name":"Sahajkot","code":"42006","panchayatCode":"22195","panchayatName":"Bhandari Khor"},{"name":"Sainji","code":"41943","panchayatCode":"","panchayatName":""},{"name":"Saliyana","code":"41928","panchayatCode":"","panchayatName":""},{"name":"Saner Laga Jingor","code":"41972","panchayatCode":"22185","panchayatName":"Aagar"},{"name":"Sankot","code":"42013","panchayatCode":"22242","panchayatName":"Malkot"},{"name":"Sare Gwar","code":"41895","panchayatCode":"243038","panchayatName":"Saregwad"},{"name":"Saring Gaon","code":"42016","panchayatCode":"22203","panchayatName":"Diwadhar"},{"name":"Saringgaon","code":"936720","panchayatCode":"","panchayatName":""},{"name":"Sarkot","code":"41893","panchayatCode":"22260","panchayatName":"Sarkot"},{"name":"Sarowar","code":"41982","panchayatCode":"243040","panchayatName":"Rangchauda"},{"name":"Sera","code":"42033","panchayatCode":"293871","panchayatName":"Sera"},{"name":"Silakot","code":"41909","panchayatCode":"22256","panchayatName":"Ramra Malla"},{"name":"Silanga/Silangi","code":"41989","panchayatCode":"22261","panchayatName":"Silanga"},{"name":"Silangi","code":"41941","panchayatCode":"","panchayatName":""},{"name":"Siman Malla","code":"41946","panchayatCode":"22265","panchayatName":"Sumerpur"},{"name":"Siman Talla","code":"41949","panchayatCode":"22265","panchayatName":"Sumerpur"},{"name":"Simliya Lagga Kunigar","code":"42008","panchayatCode":"22232","panchayatName":"Kunigad Malli"},{"name":"Sinatoli","code":"41936","panchayatCode":"259847","panchayatName":"Sintoli"},{"name":"Soniyana","code":"41938","panchayatCode":"","panchayatName":""},{"name":"Sumerpur","code":"41948","panchayatCode":"22265","panchayatName":"Sumerpur"},{"name":"Syuni Talli","code":"41981","panchayatCode":"22267","panchayatName":"Syuni Talli"},{"name":"Syunimalli","code":"41974","panchayatCode":"22266","panchayatName":"Syuni Malli"},{"name":"Taituna","code":"42038","panchayatCode":"22268","panchayatName":"Teituda"},{"name":"Tal Gaon","code":"41898","panchayatCode":"22244","panchayatName":"Maroda"},{"name":"Thala","code":"41984","panchayatCode":"22246","panchayatName":"Mehal Chauri"},{"name":"Timil Gair","code":"42005","panchayatCode":"22221","panchayatName":"Kalyani Talli"},{"name":"Tollyu Chak Latugair","code":"42029","panchayatCode":"22242","panchayatName":"Malkot"},{"name":"Uttari Jhuma Khet","code":"42049","panchayatCode":"22217","panchayatName":"Jhumakhet Uttari"},{"name":"Wadiyari Laga Kwilakh","code":"41956","panchayatCode":"22231","panchayatName":"Koylakh"},{"name":"Wasi Sem Laga Lakheri","code":"41950","panchayatCode":"22235","panchayatName":"Lakheri"},{"name":"Wasisem Laga Akshawara","code":"41968","panchayatCode":"22235","panchayatName":"Lakheri"}]