[{"name":"Kagey Khasmahal","code":"306278","panchayatCode":"","panchayatName":""},{"name":"Kashone Khasmahal","code":"306275","panchayatCode":"","panchayatName":""},{"name":"Ladam Khasmahal","code":"306280","panchayatCode":"","panchayatName":""},{"name":"Lingsay Khasmahal","code":"306282","panchayatCode":"","panchayatName":""},{"name":"Lingsaykha Khasmahal","code":"306281","panchayatCode":"","panchayatName":""},{"name":"Maria Khasmahal","code":"306279","panchayatCode":"","panchayatName":""},{"name":"Mayrong Forest","code":"306291","panchayatCode":"","panchayatName":""},{"name":"Pedong Bazar D.I.F.","code":"306276","panchayatCode":"","panchayatName":""},{"name":"Pedong Khasmahal","code":"306277","panchayatCode":"","panchayatName":""},{"name":"Rhenok Forest","code":"306283","panchayatCode":"","panchayatName":""},{"name":"Sakiyong Khasmahal","code":"306292","panchayatCode":"","panchayatName":""}]